savetheworld/__init__.py
savetheworld/email.py
savetheworld/touch.py
savetheworld-0.1.1.dist-info/DESCRIPTION.rst
savetheworld-0.1.1.dist-info/METADATA
savetheworld-0.1.1.dist-info/RECORD
savetheworld-0.1.1.dist-info/WHEEL
savetheworld-0.1.1.dist-info/metadata.json
savetheworld-0.1.1.dist-info/top_level.txt
