Metadata-Version: 2.0
Name: savetheworld
Version: 0.1.1
Summary: Useful code for the 'Save the World with code' book
Home-page: https://github.com/Lorrainbow/savetheworld
Author: Lorraine Underwood
Author-email: lorrainbow@gmail.com
License: UNKNOWN
Platform: UNKNOWN
Classifier: Programming Language :: Python :: 3
Classifier: License :: OSI Approved :: GNU General Public License v3 (GPLv3)
Classifier: Operating System :: POSIX :: Linux
Requires-Dist: touchphat
